SalesforceMinu/Funciones.py
SalesforceMinu/__init__.py
SalesforceMinu-0.0.9.dist-info/METADATA
SalesforceMinu-0.0.9.dist-info/WHEEL
SalesforceMinu-0.0.9.dist-info/top_level.txt
SalesforceMinu-0.0.9.dist-info/RECORD
