Metadata-Version: 2.1
Name: SalesforceMinu
Version: 0.0.9
Summary: Librería para extraer datos de minu en salesforce
Home-page: https://github.com/BalamCor?tab=repositories
Author: Corchado Ramos Itzae Balam
Author-email: g7_corc18@ens.cnyn.unam.mx
License: MIT
Requires-Dist: pandas
Requires-Dist: pymysql
